azure_functions_test/__init__.py
azure_functions_test/__init__.pyi
azure_functions_test/_version.py
azure_functions_test/context.py
azure_functions_test/protocols.py
azure_functions_test/py.typed
azure_functions_test/_internal/__init__.py
azure_functions_test/_internal/logging.py
azure_functions_test/_internal/serialization.py
azure_functions_test/fixtures/__init__.py
azure_functions_test/fixtures/pytest_plugin.py
azure_functions_test/mocks/__init__.py
azure_functions_test/mocks/base.py
azure_functions_test/mocks/blob.py
azure_functions_test/mocks/eventgrid.py
azure_functions_test/mocks/http.py
azure_functions_test/mocks/queue.py
azure_functions_test/mocks/servicebus.py
azure_functions_test/mocks/timer.py
azure_functions_test-1.17.0a1.dist-info/METADATA
azure_functions_test-1.17.0a1.dist-info/WHEEL
azure_functions_test-1.17.0a1.dist-info/RECORD
