Metadata-Version: 2.4
Name: azure-functions-test
Version: 1.17.0a1
Summary: Unit test Azure Functions without the runtime
Project-URL: Homepage, https://github.com/sudzxd/azure-functions-test
Project-URL: Documentation, https://sudzxd.github.io/azure-functions-test
Project-URL: Repository, https://github.com/sudzxd/azure-functions-test
Project-URL: Changelog, https://github.com/sudzxd/azure-functions-test/blob/main/CHANGELOG.md
Author-email: Sudarshan <your@email.com>
License: MIT
Keywords: azure,functions,mock,pytest,serverless,testing
Classifier: Development Status :: 3 - Alpha
Classifier: Framework :: Pytest
Classifier: Intended Audience :: Developers
Classifier: License :: OSI Approved :: MIT License
Classifier: Programming Language :: Python :: 3
Classifier: Programming Language :: Python :: 3.11
Classifier: Programming Language :: Python :: 3.12
Classifier: Programming Language :: Python :: 3.13
Classifier: Topic :: Software Development :: Testing
Classifier: Typing :: Typed
Requires-Python: >=3.11
Requires-Dist: azure-functions>=1.17.0
Requires-Dist: pydantic>=2.0
Provides-Extra: dev
Requires-Dist: bandit>=1.7; extra == 'dev'
Requires-Dist: pip-audit>=2.7; extra == 'dev'
Requires-Dist: pyright>=1.1.350; extra == 'dev'
Requires-Dist: pytest-cov>=4.0; extra == 'dev'
Requires-Dist: pytest>=8.0; extra == 'dev'
Requires-Dist: ruff>=0.3; extra == 'dev'
Requires-Dist: twine>=5.0; extra == 'dev'
Provides-Extra: docs
Requires-Dist: mkdocs-material>=9.5; extra == 'docs'
Requires-Dist: mkdocs>=1.5; extra == 'docs'
Requires-Dist: mkdocstrings[python]>=0.24; extra == 'docs'
